aviator_math/__init__.py
aviator_math/coef_generation.py
aviator_math/cutting_methods.py
aviator_math/data/cdf.csv
aviator_math-0.1.2.dist-info/METADATA
aviator_math-0.1.2.dist-info/WHEEL
aviator_math-0.1.2.dist-info/RECORD
